moneyed/__init__.py
moneyed/classes.py
moneyed/l10n.py
moneyed/py.typed
moneyed/utils.py
py_moneyed-3.0.dist-info/LICENSE
py_moneyed-3.0.dist-info/METADATA
py_moneyed-3.0.dist-info/WHEEL
py_moneyed-3.0.dist-info/top_level.txt
py_moneyed-3.0.dist-info/RECORD
