Metadata-Version: 2.1
Name: py-moneyed
Version: 3.0
Summary: Provides Currency and Money classes for use in your Python code.
Author: Kai
Author-email: k@limist.com
Maintainer: Dmitry Dygalo
Maintainer-email: dadygalo@gmail.com
License: BSD
Project-URL: Homepage, http://github.com/py-moneyed/py-moneyed
Project-URL: Documentation, https://py-moneyed.readthedocs.io/en/latest/
Keywords: money currency class abstraction
Platform: any
Classifier: Programming Language :: Python
Classifier: Programming Language :: Python :: 3.7
Classifier: Programming Language :: Python :: 3.8
Classifier: Programming Language :: Python :: 3.9
Classifier: Programming Language :: Python :: 3.10
Classifier: Programming Language :: Python :: 3.11
Classifier: Programming Language :: Python :: Implementation :: CPython
Classifier: Programming Language :: Python :: Implementation :: PyPy
Classifier: License :: OSI Approved :: BSD License
Classifier: Operating System :: OS Independent
Classifier: Development Status :: 6 - Mature
Classifier: Environment :: Other Environment
Classifier: Intended Audience :: Developers
Classifier: Topic :: Office/Business :: Financial
Classifier: Topic :: Software Development :: Libraries :: Python Modules
Requires-Python: >=3.7
Provides-Extra: tests
Provides-Extra: type-tests
License-File: LICENSE
